ykpstools/__init__.py
ykpstools/__main__.py
ykpstools/exceptions.py
ykpstools/page.py
ykpstools/user.py
ykpstools-1.0.2.1.dist-info/LICENSE
ykpstools-1.0.2.1.dist-info/METADATA
ykpstools-1.0.2.1.dist-info/WHEEL
ykpstools-1.0.2.1.dist-info/top_level.txt
ykpstools-1.0.2.1.dist-info/RECORD
