Metadata-Version: 2.1
Name: ykpstools
Version: 1.0.2.1
Summary: Tools & utilities associated with online logins of YKPS.
Home-page: https://github.com/HanwenZhu/ykpstools
Author: Thomas Zhu
License: MIT
Platform: UNKNOWN
Classifier: Development Status :: 1 - Planning
Classifier: Programming Language :: Python :: 3
Classifier: License :: OSI Approved :: MIT License
Classifier: Operating System :: OS Independent
Requires-Python: >=3
Requires-Dist: requests
Requires-Dist: beautifulsoup4
Requires-Dist: lxml
